gitlab/__init__.py
gitlab/base.py
gitlab/cli.py
gitlab/config.py
gitlab/const.py
gitlab/exceptions.py
gitlab/mixins.py
gitlab/types.py
gitlab/utils.py
gitlab/tests/__init__.py
gitlab/tests/test_base.py
gitlab/tests/test_cli.py
gitlab/tests/test_config.py
gitlab/tests/test_gitlab.py
gitlab/tests/test_gitlabobject.py
gitlab/tests/test_manager.py
gitlab/tests/test_mixins.py
gitlab/tests/test_types.py
gitlab/v3/__init__.py
gitlab/v3/cli.py
gitlab/v3/objects.py
gitlab/v4/__init__.py
gitlab/v4/cli.py
gitlab/v4/objects.py
python_gitlab_patch-1.4.0.1.dist-info/AUTHORS
python_gitlab_patch-1.4.0.1.dist-info/COPYING
python_gitlab_patch-1.4.0.1.dist-info/METADATA
python_gitlab_patch-1.4.0.1.dist-info/WHEEL
python_gitlab_patch-1.4.0.1.dist-info/entry_points.txt
python_gitlab_patch-1.4.0.1.dist-info/top_level.txt
python_gitlab_patch-1.4.0.1.dist-info/RECORD
